Workbook

Sheet 收支明细
A1: 日期 | B1: 类型 | C1: 分类 | D1: 说明 | E1: 金额(元) | G1: 汇总
A2: 46237 | B2: 支出 | C2: 餐饮 | D2: 日常饮食 | E2: 1800 | G2: 收入合计 | H2: =SUMIF(B2:B11,"收入",E2:E11) -> 14000
A3: 46240 | B3: 支出 | C3: 交通 | D3: 地铁与打车 | E3: 450 | G3: 支出合计 | H3: =SUMIF(B2:B11,"支出",E2:E11) -> 7600
A4: 46242 | B4: 支出 | C4: 居住 | D4: 房租水电 | E4: 3200 | G4: 本月结余 | H4: =H2-H3 -> 6400
A5: 46244 | B5: 支出 | C5: 购物 | D5: 日用品 | E5: 600
A6: 46246 | B6: 支出 | C6: 娱乐 | D6: 电影游戏 | E6: 300
A7: 46249 | B7: 支出 | C7: 医疗 | D7: 年度体检 | E7: 400
A8: 46252 | B8: 支出 | C8: 教育 | D8: 线上课程 | E8: 500
A9: 46256 | B9: 支出 | C9: 其他 | D9: 人情往来 | E9: 350
A10: 46239 | B10: 收入 | C10: 工资 | D10: 8月工资 | E10: 12000
A11: 46239 | B11: 收入 | C11: 副业 | D11: 设计稿酬 | E11: 2000

Sheet 月度预算
A1: 分类 | B1: 预算(元) | C1: 实际支出(元) | D1: 结余(元)
A2: 餐饮 | B2: 2000 | C2: =SUMIFS(收支明细!$E$2:$E$11,收支明细!$B$2:$B$11,"支出",收支明细!$C$2:$C$11,A2) -> 1800 | D2: =B2-C2 -> 200
A3: 交通 | B3: 500 | C3: =SUMIFS(收支明细!$E$2:$E$11,收支明细!$B$2:$B$11,"支出",收支明细!$C$2:$C$11,A3) -> 450 | D3: =B3-C3 -> 50
A4: 居住 | B4: 3200 | C4: =SUMIFS(收支明细!$E$2:$E$11,收支明细!$B$2:$B$11,"支出",收支明细!$C$2:$C$11,A4) -> 3200 | D4: =B4-C4 -> 0
A5: 购物 | B5: 800 | C5: =SUMIFS(收支明细!$E$2:$E$11,收支明细!$B$2:$B$11,"支出",收支明细!$C$2:$C$11,A5) -> 600 | D5: =B5-C5 -> 200
A6: 娱乐 | B6: 500 | C6: =SUMIFS(收支明细!$E$2:$E$11,收支明细!$B$2:$B$11,"支出",收支明细!$C$2:$C$11,A6) -> 300 | D6: =B6-C6 -> 200
A7: 医疗 | B7: 500 | C7: =SUMIFS(收支明细!$E$2:$E$11,收支明细!$B$2:$B$11,"支出",收支明细!$C$2:$C$11,A7) -> 400 | D7: =B7-C7 -> 100
A8: 教育 | B8: 600 | C8: =SUMIFS(收支明细!$E$2:$E$11,收支明细!$B$2:$B$11,"支出",收支明细!$C$2:$C$11,A8) -> 500 | D8: =B8-C8 -> 100
A9: 其他 | B9: 400 | C9: =SUMIFS(收支明细!$E$2:$E$11,收支明细!$B$2:$B$11,"支出",收支明细!$C$2:$C$11,A9) -> 350 | D9: =B9-C9 -> 50
A10: 合计 | B10: =SUM(B2:B9) -> 8500 | C10: =SUM(C2:C9) -> 7600 | D10: =SUM(D2:D9) -> 900
